mocknet_ssh/__init__.py
mocknet_ssh/__main__.py
mocknet_ssh/api.py
mocknet_ssh/cli.py
mocknet_ssh/handlers/__init__.py
mocknet_ssh/handlers/cisco_asa.py
mocknet_ssh/handlers/cisco_ios.py
mocknet_ssh/handlers/cisco_nxos.py
mocknet_ssh/handlers/command_output/cisco_asa/cisco_asa_dir.raw
mocknet_ssh/handlers/command_output/cisco_asa/cisco_asa_dir2.raw
mocknet_ssh/handlers/command_output/cisco_asa/cisco_asa_ping.raw
mocknet_ssh/handlers/command_output/cisco_asa/cisco_asa_ping_mix.raw
mocknet_ssh/handlers/command_output/cisco_asa/cisco_asa_ping_quench.raw
mocknet_ssh/handlers/command_output/cisco_asa/cisco_asa_ping_unreachable.raw
mocknet_ssh/handlers/command_output/cisco_asa/cisco_asa_show_access-list.raw
mocknet_ssh/handlers/command_output/cisco_asa/cisco_asa_show_access-list3.raw
mocknet_ssh/handlers/command_output/cisco_asa/cisco_asa_show_access-list_4.raw
mocknet_ssh/handlers/command_output/cisco_asa/cisco_asa_show_access-list_brief.raw
mocknet_ssh/handlers/command_output/cisco_asa/cisco_asa_show_access-list_update.raw
mocknet_ssh/handlers/command_output/cisco_asa/cisco_asa_show_access-list_update2.raw
mocknet_ssh/handlers/command_output/cisco_asa/cisco_asa_show_arp.raw
mocknet_ssh/handlers/command_output/cisco_asa/cisco_asa_show_asp_drop.raw
mocknet_ssh/handlers/command_output/cisco_asa/cisco_asa_show_asp_drop2.raw
mocknet_ssh/handlers/command_output/cisco_asa/cisco_asa_show_asp_table_vpn-context_detail.raw
mocknet_ssh/handlers/command_output/cisco_asa/cisco_asa_show_cpu_usage_detailed.raw
mocknet_ssh/handlers/command_output/cisco_asa/cisco_asa_show_crypto_ikev1_sa_detail.raw
mocknet_ssh/handlers/command_output/cisco_asa/cisco_asa_show_crypto_ipsec_sa.raw
mocknet_ssh/handlers/command_output/cisco_asa/cisco_asa_show_failover.raw
mocknet_ssh/handlers/command_output/cisco_asa/cisco_asa_show_failover1.raw
mocknet_ssh/handlers/command_output/cisco_asa/cisco_asa_show_failover2.raw
mocknet_ssh/handlers/command_output/cisco_asa/cisco_asa_show_failover5505.raw
mocknet_ssh-0.0.1.dist-info/LICENSE.md
mocknet_ssh-0.0.1.dist-info/METADATA
mocknet_ssh-0.0.1.dist-info/WHEEL
mocknet_ssh-0.0.1.dist-info/RECORD
