Metadata-Version: 2.3
Name: mocknet_ssh
Version: 0.0.1
Summary: A reusable SSH mock server framework for simulating network devices like Cisco IOS, Palo Alto PAN-OS, etc.
License: Apache-2.0
Author: Sascha Schwarz
Author-email: sascha@providerhoelle.de
Requires-Python: >=3.12,<4.0
Classifier: License :: OSI Approved :: Apache Software License
Classifier: Programming Language :: Python :: 3
Classifier: Programming Language :: Python :: 3.12
Classifier: Programming Language :: Python :: 3.13
Requires-Dist: asyncssh (>=2.20.0,<3.0.0)
Project-URL: Repository, https://github.com/SaschaSchwarzK/mocknet_ssh
